mdapi/__init__.py
mdapi/__main__.py
mdapi/cli.py
mdapi/endpoints.py
mdapi/exceptions.py
mdapi/mdapi.py
mdapi/util.py
mdapi/api/__init__.py
mdapi/api/account.py
mdapi/api/auth.py
mdapi/api/author.py
mdapi/api/base.py
mdapi/api/chapter.py
mdapi/api/cover.py
mdapi/api/group.py
mdapi/api/list.py
mdapi/api/manga.py
mdapi/api/misc.py
mdapi/api/upload.py
mdapi/api/user.py
mdex-0.0.14.data/scripts/mdex.py
mdex-0.0.14.dist-info/METADATA
mdex-0.0.14.dist-info/WHEEL
mdex-0.0.14.dist-info/top_level.txt
mdex-0.0.14.dist-info/RECORD
